textract_pycon/__init__.py
textract_pycon/py.typed
textract_pycon/textract_pycon.py
textract_pycon-0.1.0.dist-info/WHEEL
textract_pycon-0.1.0.dist-info/METADATA
textract_pycon-0.1.0.dist-info/RECORD
