Metadata-Version: 2.3
Name: textract-pycon
Version: 0.1.0
Summary: PyCon Textract workshop
Author: Carlo van Overbeek
Author-email: Carlo van Overbeek <cvanoverbeek@schubergphilis.com>
Classifier: License :: OSI Approved :: Apache Software License
Classifier: Programming Language :: Python :: 3.12
Requires-Dist: boto3>=1.40.47
Requires-Python: >=3.12
